a7dtester.py
a7dtester-0.0.4.dist-info/METADATA
a7dtester-0.0.4.dist-info/WHEEL
a7dtester-0.0.4.dist-info/entry_points.txt
a7dtester-0.0.4.dist-info/top_level.txt
a7dtester-0.0.4.dist-info/RECORD
