Metadata-Version: 2.1
Name: a7dtester
Version: 0.0.4
Summary: simple test runner
Home-page: UNKNOWN
Author: Uladzislau Khamkou
License: UNKNOWN
Platform: UNKNOWN
Requires-Python: >=3.6
Requires-Dist: a7d (>=0.0.5)
